database_automation/__init__.py
database_automation/mongo_crud.py
hemant_193_database_setup-0.0.8.dist-info/METADATA
hemant_193_database_setup-0.0.8.dist-info/WHEEL
hemant_193_database_setup-0.0.8.dist-info/top_level.txt
hemant_193_database_setup-0.0.8.dist-info/RECORD
